sam_plot_extraction/__init__.py
sam_plot_extraction/plot_extraction.py
sam_plot_extraction-0.2.4.dist-info/LICENSE
sam_plot_extraction-0.2.4.dist-info/METADATA
sam_plot_extraction-0.2.4.dist-info/WHEEL
sam_plot_extraction-0.2.4.dist-info/top_level.txt
sam_plot_extraction-0.2.4.dist-info/RECORD
